wxyz/dvcs/__init__.py
wxyz/dvcs/_version.py
wxyz/dvcs/base.py
wxyz/dvcs/install.json
wxyz/dvcs/widget_watch.py
wxyz/dvcs/js/LICENSE.txt
wxyz/dvcs/js/README.md
wxyz/dvcs/js/package.json
wxyz/dvcs/labextension/package.json
wxyz/dvcs/labextension/static/333.64cb1f1f5e38473eb9ea.js
wxyz/dvcs/labextension/static/568.af12d4d44afd18f59416.js
wxyz/dvcs/labextension/static/572.83c5c9143eb3bf017298.js
wxyz/dvcs/labextension/static/remoteEntry.27bcd85313dd1f91b8c5.js
wxyz/dvcs/labextension/static/style.js
wxyz/dvcs/repos/__init__.py
wxyz/dvcs/repos/repo_base.py
wxyz/dvcs/repos/repo_git.py
wxyz/dvcs/tools/__init__.py
wxyz/dvcs/tools/tool_commits.py
wxyz/dvcs/tools/tool_heads.py
wxyz/dvcs/tools/tool_remotes.py
wxyz/dvcs/tools/tool_timetravel.py
wxyz/dvcs/tools/utils.py
wxyz/dvcs/trackers/__init__.py
wxyz/dvcs/trackers/tracker_base.py
wxyz/dvcs/trackers/tracker_json.py
wxyz/dvcs/trackers/tracker_yaml.py
wxyz_dvcs-0.5.1.data/data/share/jupyter/labextensions/@deathbeds/wxyz-dvcs/install.json
wxyz_dvcs-0.5.1.data/data/share/jupyter/labextensions/@deathbeds/wxyz-dvcs/package.json
wxyz_dvcs-0.5.1.data/data/share/jupyter/labextensions/@deathbeds/wxyz-dvcs/static/333.64cb1f1f5e38473eb9ea.js
wxyz_dvcs-0.5.1.data/data/share/jupyter/labextensions/@deathbeds/wxyz-dvcs/static/568.af12d4d44afd18f59416.js
wxyz_dvcs-0.5.1.data/data/share/jupyter/labextensions/@deathbeds/wxyz-dvcs/static/572.83c5c9143eb3bf017298.js
wxyz_dvcs-0.5.1.data/data/share/jupyter/labextensions/@deathbeds/wxyz-dvcs/static/remoteEntry.27bcd85313dd1f91b8c5.js
wxyz_dvcs-0.5.1.data/data/share/jupyter/labextensions/@deathbeds/wxyz-dvcs/static/style.js
wxyz_dvcs-0.5.1.dist-info/LICENSE.txt
wxyz_dvcs-0.5.1.dist-info/METADATA
wxyz_dvcs-0.5.1.dist-info/WHEEL
wxyz_dvcs-0.5.1.dist-info/top_level.txt
wxyz_dvcs-0.5.1.dist-info/RECORD
